aind_ephys_utils/__init__.py
aind_ephys_utils/align.py
aind_ephys_utils/metrics.py
aind_ephys_utils/sort.py
aind_ephys_utils-0.0.15.dist-info/LICENSE
aind_ephys_utils-0.0.15.dist-info/METADATA
aind_ephys_utils-0.0.15.dist-info/WHEEL
aind_ephys_utils-0.0.15.dist-info/top_level.txt
aind_ephys_utils-0.0.15.dist-info/RECORD
